MANIFEST.in
README.md
setup.py
django_bootstrap_markdown/__init__.py
django_bootstrap_markdown/admin.py
django_bootstrap_markdown/apps.py
django_bootstrap_markdown/forms.py
django_bootstrap_markdown/models.py
django_bootstrap_markdown/urls.py
django_bootstrap_markdown/views.py
django_bootstrap_markdown/widgets.py
django_bootstrap_markdown.egg-info/PKG-INFO
django_bootstrap_markdown.egg-info/SOURCES.txt
django_bootstrap_markdown.egg-info/dependency_links.txt
django_bootstrap_markdown.egg-info/not-zip-safe
django_bootstrap_markdown.egg-info/requires.txt
django_bootstrap_markdown.egg-info/top_level.txt
django_bootstrap_markdown/locale/en/LC_MESSAGES/django.mo
django_bootstrap_markdown/locale/es/LC_MESSAGES/django.mo
django_bootstrap_markdown/static/.DS_Store
django_bootstrap_markdown/static/css/django_bootstrap_markdown.css
django_bootstrap_markdown/static/js/django_bootstrap_markdown.js
django_bootstrap_markdown/static/js/jquery.textarea.min.js
django_bootstrap_markdown/templates/.DS_Store
django_bootstrap_markdown/templates/django_bootstrap_markdown/.DS_Store
django_bootstrap_markdown/templates/django_bootstrap_markdown/markdown_form.html
django_bootstrap_markdown/templates/django_bootstrap_markdown/markdown_image.html
django_bootstrap_markdown/templates/django_bootstrap_markdown/markdown_library.html
django_bootstrap_markdown/templates/django_bootstrap_markdown/widget.html