Metadata-Version: 1.1
Name: django-bootstrap-markdown
Version: 1.8.0
Summary: An extension of the Django Textarea widget made for
Home-page: http://thegoods.aj7may.com/django-bootstrap-markdown
Author: A.J. May
Author-email: aj7may@gmail.com
License: MIT License
Keywords: django bootstrap markdown live preview auto scroll
Platform: UNKNOWN
Classifier: Development Status :: 5 - Production/Stable
Classifier: Environment :: Web Environment
Classifier: Framework :: Django
Classifier: Intended Audience :: Developers
Classifier: License :: OSI Approved :: MIT License
Classifier: Operating System :: OS Independent
